{
  "parent": "minecraft:recipes/root",
  "criteria": {
    "has_serpentinite": {
      "conditions": {
        "items": [
          {
            "items": [
              "mc-recrafted:serpentinite"
            ]
          }
        ]
      },
      "trigger": "minecraft:inventory_changed"
    },
    "has_the_recipe": {
      "conditions": {
        "recipe": "mc-recrafted:serpentinite_block"
      },
      "trigger": "minecraft:recipe_unlocked"
    }
  },
  "requirements": [
    [
      "has_serpentinite",
      "has_the_recipe"
    ]
  ],
  "rewards": {
    "recipes": [
      "mc-recrafted:serpentinite_block"
    ]
  },
  "sends_telemetry_event": false
}